__init__.py
twitcasting_realtime_chat.py
twitcasting_realtime_chat-0.1.0.dist-info/LICENSE
twitcasting_realtime_chat-0.1.0.dist-info/METADATA
twitcasting_realtime_chat-0.1.0.dist-info/WHEEL
twitcasting_realtime_chat-0.1.0.dist-info/top_level.txt
twitcasting_realtime_chat-0.1.0.dist-info/RECORD
