Metadata-Version: 2.1
Name: twitcasting-realtime-chat
Version: 0.1.0
Summary: An unofficial comment viewer CLI for TwitCasting lives
Home-page: https://github.com/kkent030315/twitcasting-realtime-chat
Author: Kento Oki
Author-email: hrn832@protonmail.com
License: UNKNOWN
Platform: UNKNOWN
Classifier: Development Status :: 5 - Production/Stable
Classifier: Topic :: Utilities
Classifier: Programming Language :: Python
Classifier: Programming Language :: Python :: 3
Classifier: Programming Language :: Python :: 3 :: Only
Classifier: Environment :: Console
Classifier: Intended Audience :: Developers
Classifier: License :: OSI Approved :: MIT License
Classifier: Operating System :: POSIX :: Linux
Classifier: Operating System :: Unix
Classifier: Operating System :: MacOS
Classifier: Operating System :: Microsoft :: Windows
Requires-Python: >=3.6
Requires-Dist: twitcasting-py
Requires-Dist: websocket-client
Requires-Dist: cursor
